salure_tfx_extensions/__init__.py
salure_tfx_extensions/model.py
salure_tfx_extensions/pipeline.py
salure_tfx_extensions/preprocessing_utils.py
salure_tfx_extensions/components/__init__.py
salure_tfx_extensions/components/model_validator/__init__.py
salure_tfx_extensions/components/model_validator/component.py
salure_tfx_extensions/components/model_validator/driver.py
salure_tfx_extensions/components/model_validator/executor.py
salure_tfx_extensions/components/mysql_example_gen/__init__.py
salure_tfx_extensions/components/mysql_example_gen/component.py
salure_tfx_extensions/components/mysql_example_gen/executor.py
salure_tfx_extensions/io/__init__.py
salure_tfx_extensions/io/db.py
salure_tfx_extensions/proto/__init__.py
salure_tfx_extensions/proto/mysql_config.proto
salure_tfx_extensions/proto/mysql_config_pb2.py
salure_tfx_extensions-0.0.34.dist-info/METADATA
salure_tfx_extensions-0.0.34.dist-info/WHEEL
salure_tfx_extensions-0.0.34.dist-info/top_level.txt
salure_tfx_extensions-0.0.34.dist-info/RECORD
