Metadata-Version: 2.1
Name: salure-tfx-extensions
Version: 0.0.34
Summary: TFX components, helper functions and pipeline definition, developed by Salure
Home-page: UNKNOWN
Author: Salure
Author-email: bi@salure.nl
License: Salure License
Platform: UNKNOWN
Requires-Dist: tfx (<0.15,>=0.14.0rc1)
Requires-Dist: tensorflow (==1.14.0)
Requires-Dist: beam-nuggets (<0.16,>=0.15.1)
